rflink/__init__.py
rflink/__main__.py
rflink/parser.py
rflink/protocol.py
rflink/py.typed
rflink-0.0.67.dist-info/licenses/LICENCE
rflinkproxy/__init__.py
rflinkproxy/__main__.py
rflink-0.0.67.dist-info/METADATA
rflink-0.0.67.dist-info/WHEEL
rflink-0.0.67.dist-info/entry_points.txt
rflink-0.0.67.dist-info/top_level.txt
rflink-0.0.67.dist-info/RECORD
