Metadata-Version: 2.4
Name: rflink
Version: 0.0.67
Summary: Library and CLI tools for interacting with RFlink 433MHz transceiver.
Home-page: https://github.com/aequitas/python-rflink
Author: Johan Bloemberg
Author-email: github@ijohan.nl
License: MIT
Project-URL: Release notes, https://github.com/aequitas/python-rflink/releases
Keywords: rflink 433mhz domotica
Classifier: Development Status :: 3 - Alpha
Classifier: Intended Audience :: Developers
Classifier: License :: OSI Approved :: MIT License
Classifier: Programming Language :: Python :: 2.7
Classifier: Programming Language :: Python :: 3.6
Classifier: Programming Language :: Python :: 3.7
Classifier: Programming Language :: Python :: 3.8
Classifier: Programming Language :: Python :: 3.9
License-File: LICENCE
Requires-Dist: docopt
Requires-Dist: pyserial
Requires-Dist: pyserial-asyncio-fast
Requires-Dist: typing; python_version < "3.5"
Requires-Dist: async_timeout; python_version < "3.11"
Dynamic: author
Dynamic: author-email
Dynamic: classifier
Dynamic: description
Dynamic: home-page
Dynamic: keywords
Dynamic: license
Dynamic: license-file
Dynamic: project-url
Dynamic: requires-dist
Dynamic: summary
